globomap_plugin_healthcheck
