Metadata-Version: 1.0
Name: globomap-plugin-healthcheck
Version: 0.1.1
Summary: Zabbix status plugin on globomap-api
Home-page: https://gitlab.globoi.com/sergios/globomap-plugin-healthcheck
Author: Storm
Author-email: storm@corp.globo.com
License: UNKNOWN
Platform: UNKNOWN
